Workbook

Sheet Periodika
B2: Total investment | C2: USD | D2: 200000
B3: app cost | C3: USD | D3: =D2*0.3 | G3: =100*10^6/G6
B5: Metric | C5: Unit | D5: 2016 | E5: 2017 | F5: 2018 | G5: 2019 | H5: 2020 | I5: 2021 | J5: 2022 | K5: 2023 | L5: Total 2016-2019 | M5: Comments
B6: Exchange rate | C6: RUB:USD | D6: 67 | E6: 58 | F6: 63 | G6: 64.7 | H6: 72.17 | I6: 73.6 | J6: 68.5 | K6: 85.3
B7: Revenue | C7: RUB
B8: Revenue | C8: USD | D8: =7.34*10^6/D6 | E8: =28.9*10^6/E6 | F8: =52.2*10^6/F6 | G8: =58.14*10^6/G6 | H8: =89.26*10^6/H6 | I8: =125.71*10^6/I6 | J8: =176.13*10^6/J6 | K8: =287.78*10^6/K6 | L8: =_xlfn.RRI($G$5-$D$5,D8,G8)
B9: Average check | C9: USD | D9: =1500/D6 | E9: =E18/E6 | F9: 44 | G9: =2900/G6
B10: Number of orders | C10: pcs/year | D10: =D8/D9 | E10: =E8/E9 | F10: =F8/F9 | G10: =G8/G9 | L10: =SUM(D10:G10) | N10: 72000 | O10: =L10/N10
B11: Number of orders | C11: pcs/day | D11: =D10/365 | E11: =E10/365 | F11: =F10/365 | G11: =G10/365
B13: Profit | C13: mnRUB | D13: -4.25 | E13: -1.81 | F13: 4.95 | G13: 4.15 | H13: 4.22 | I13: 4.45 | J13: 6.45 | K13: 24.73 | M13: https://companies.rbc.ru/id/1157746985285-ooo-periodika-press/
B14: Profit | C14: USD | D14: =D13/D6*10^6 | E14: =E13/E6*10^6 | F14: =F13/F6*10^6 | G14: =G13/G6*10^6 | H14: =H13/H6*10^6 | I14: =I13/I6*10^6 | J14: =J13/J6*10^6 | K14: =K13/K6*10^6
D15: =D14/D8 | E15: =E14/E8 | F15: =F14/F8 | G15: =G14/G8 | H15: =H14/H8 | I15: =I14/I8 | J15: =J14/J8 | K15: =K14/K8
B17: Photobook hard cloth binding 20x20, 40 pages | C17: RUB | D17: n.a | E17: 2990 | F17: =E17 | G17: =F17 | H17: =G17
B18: Photobook hard photo cover, 20x20, 40 pages | D18: n.a | E18: 2490 | F18: =E18 | G18: =F18 | H18: =G18
B19: Photobook soft cover, 14x14, 40 pages | D19: 1490 | E19: 1490 | F19: 1790 | G19: =F19 | H19: =G19
B20: Zinbook (travel/thematic mini-book), 24pages | G20: 1490 | H20: =G20
B21: Photobook hard cloth binding with cover photo, 20x20, 80 pages | G21: 4490 | H21: =G21 | L21: =200*12
B22: Photobook hard photo cover, 20x20, 80 pages | G22: 3990 | H22: =G22
B23: New line of business: Kids | G23: xx
B24: Postcards 10x15, 24pack | E24: 990 | H24: 1290
B26: Headcount (full time) | G26: 3
B28: Digital marketing | C28: % of revenue | D28: 0.1 | E28: =D28 | F28: =E28 | G28: =F28
B29: Influencer marketing | C29: % of revenue | D29: 0.05 | E29: 0.05 | F29: 0.05 | G29: 0.05
B31: Digital marketing
B32: Influencer marketing
C34: "automated pre-print editing"
C35: SLA: priting period 2 days + 1day delivery
C36: over 4 years changed 4 typographies and 2 delivery services
C37: own typography is not the option: very expensive
C38: focus is full automation: clients create albums and order automatically goes to server. Every morning from there orders go to print. On evening company gathers ready products to sorting center and then send them to all customers
C39: Initially targeted hipsters but then broadened TA: many older people preferred tactil, sustaintalbe things over digital
C40: Participated and showed products at events like Picnic Afisha (music festival)
C41: offset type of printing vs photopaper?
C42: no SEO optimization invesments *if someone searches "buy photobook" - probably not our target audience
C43: Marketing: insta, bloggers, target, content marketing -- outsource to agencies
C44: During 1st year: gave beta access to app to photo bloggers, photographers, photo communities -- many tested, wrote their reviews -- generated traffic
C45: no discounts.only once a year 1+1
... C59: 6. didn't compare suppliers prices

Sheet Business case - old
D2: hard input
D3: link to Assumptions tab
D4: calc
D5: not used for calcs
B9: # | D9: Metric | E9: Unit | G9: 3Q 2026 | H9: 4Q 2026 | I9: 1Q 2027 | J9: 2Q 2027 | K9: 3Q 2027 | L9: 4Q2027 | M9: 2026 | N9: =M9+1 | O9: =N9+1 | P9: 2029 | R9: Comments
B11: 1 | D11: Revenue | M11: =M16*M18+M20*M17 | N11: =N16*N18+N20*N17 | O11: =O16*O18+O20*O17 | P11: =P16*P18+P20*P17
D13: Number of orders per month | G13: 0 | H13: 50 | I13: 75 | J13: 75 | K13: 100 | L13: 100 | M13: 100 | N13: 300 | O13: 500 | P13: 700 | R13: Directional, entering other markets in EU
D14: Number of orders per year | M14: =M13*12 | N14: =N13*12 | O14: =O13*12 | P14: =P13*12
D16: B2C | E16: # orders | M16: =M14-M17 | N16: =N14-N17 | O16: =O14-O17 | P16: =P14-P17
D17: B2B | E17: # orders | M17: =M14*Assumptions!F$84 | N17: =N14*Assumptions!G$84 | O17: =O14*Assumptions!H$84 | P17: =P14*Assumptions!I$84
D18: Average check B2C (excl VAT) | E18: EUR | M18: 50 | N18: =M18*(1+Assumptions!$F$11) | O18: =N18*(1+Assumptions!$F$11) | P18: =O18*(1+Assumptions!$F$11) | R18: Premium to competition
D19: Average check B2C (with VAT) | E19: EUR | M19: =M18*(1+Assumptions!$F$12) | N19: =N18*(1+Assumptions!$F$12) | O19: =O18*(1+Assumptions!$F$12) | P19: =P18*(1+Assumptions!$F$12)
D20: Average check B2B (excl VAT) | E20: EUR | M20: =M18*(1+Assumptions!F$83) | N20: =N18*(1+Assumptions!G$83) | O20: =O18*(1+Assumptions!H$83) | P20: =P18*(1+Assumptions!I$83) | R20: assuming capability to charge more from B2B
D21: Average check B2B (with VAT) | E21: EUR | M21: =M20*(1+Assumptions!$F$12) | N21: =N20*(1+Assumptions!$F$12) | O21: =O20*(1+Assumptions!$F$12) | P21: =P20*(1+Assumptions!$F$12)
D23: Sales | M23: =M24+M25 | N23: =N24+N25 | O23: =O24+O25 | P23: =P24+P25
D24: B2C | M24: =M16*M18 | N24: =N16*N18 | O24: =O16*O18 | P24: =P16*P18
D25: B2B | M25: =M17*M20 | N25: =N17*N20 | O25: =O17*O20 | P25: =P17*P20
D26: Defect % | M26: 0.02 | N26: 0.02 | O26: 0.02 | P26: 0.02 | R26: benchmarks
D27: Net sales | M27: =M23*(1-M26) | N27: =N23*(1-N26) | O27: =O23*(1-O26) | P27: =P23*(1-P26)
B29: 2 | D29: OPEX | M29: =M78 | N29: =N78 | O29: =O78 | P29: =P78
D31: COGS | M31: =SUM(M32:M37) | N31: =SUM(N32:N37) | O31: =SUM(O32:O37) | P31: =SUM(P32:P37)
D32: Printing | M32: {=-INDEX(Assumptions!$F$37:$N$37,,MATCH(M$13,Assumptions!$F$20:$N$20,0))*M14} | N32: {=-INDEX(Assumptions!$F$37:$N$37,,MATCH(N$13,Assumptions!$F$20:$N$20,0))*N14} | O32: {=-INDEX(Assumptions!$F$37:$N$37,,MATCH(O$13,Assumptions!$F$20:$N$20,0))*O14} | P32: {=-INDEX(Assumptions!$F$37:$N$37,,MATCH(P$13,Assumptions!$F$20:$N$20,0))*P14} | R32: from Elanders
D33: Packaging | M33: {=-INDEX(Assumptions!$F$50:$N$50,,MATCH(M$13,Assumptions!$F$20:$N$20,0))*M14} | N33: {=-INDEX(Assumptions!$F$50:$N$50,,MATCH(N$13,Assumptions!$F$20:$N$20,0))*N14} | O33: {=-INDEX(Assumptions!$F$50:$N$50,,MATCH(O$13,Assumptions!$F$20:$N$20,0))*O14} | P33: {=-INDEX(Assumptions!$F$50:$N$50,,MATCH(P$13,Assumptions!$F$20:$N$20,0))*P14} | R33: from Elanders
D34: Cloud | M34: {=-INDEX(Assumptions!$F$51:$N$51,,MATCH(M$13,Assumptions!$F$20:$N$20,0))*M14} | N34: {=-INDEX(Assumptions!$F$51:$N$51,,MATCH(N$13,Assumptions!$F$20:$N$20,0))*N14} | O34: {=-INDEX(Assumptions!$F$51:$N$51,,MATCH(O$13,Assumptions!$F$20:$N$20,0))*O14} | P34: {=-INDEX(Assumptions!$F$51:$N$51,,MATCH(P$13,Assumptions!$F$20:$N$20,0))*P14} | R34: from Elanders
D35: Delivery | M35: {=-INDEX(Assumptions!$F$52:$N$52,,MATCH(M$13,Assumptions!$F$20:$N$20,0))*M14} | N35: {=-INDEX(Assumptions!$F$52:$N$52,,MATCH(N$13,Assumptions!$F$20:$N$20,0))*N14} | O35: {=-INDEX(Assumptions!$F$52:$N$52,,MATCH(O$13,Assumptions!$F$20:$N$20,0))*O14} | P35: {=-INDEX(Assumptions!$F$52:$N$52,,MATCH(P$13,Assumptions!$F$20:$N$20,0))*P14} | R35: from Elanders
D36: Royalty to artists | M36: =-Assumptions!$F$77*(M14*M18) | N36: =-Assumptions!$F$77*(N14*N18) | O36: =-Assumptions!$F$77*(O14*O18) | P36: =-Assumptions!$F$77*(P14*P18) | R36: assumed, cross-checked with artists
D37: Payment processing | M37: =-(SUMPRODUCT(Assumptions!$F$58:$F$60,Assumptions!$F$68:$F$70)/SUM(Assumptions!$F$68:$F$70)*M11+ SUMPRODUCT(Assumptions!$F$62:$F$64,Assumptions!$F$68:$F$70)/SUM(Assumptions!$F$68:$F$70)*M14) | N37: =-(SUMPRODUCT(Assumptions!$F$58:$F$60,Assumptions!$F$68:$F$70)/SUM(Assumptions!$F$68:$F$70)*N11+ SUMPRODUCT(Assumptions!$F$62:$F$64,Assumptions!$F$68:$F$70)/SUM(Assumptions!$F$68:$F$70)*N14) | O37: =-(SUMPRODUCT(Assumptions!$F$58:$F$60,Assumptions!$F$68:$F$70)/SUM(Assumptions!$F$68:$F$70)*O11+ SUMPRODUCT(Assumptions!$F$62:$F$64,Assumptions!$F$68:$F$70)/SUM(Assumptions!$F$68:$F$70)*O14) | P37: =-(SUMPRODUCT(Assumptions!$F$58:$F$60,Assumptions!$F$68:$F$70)/SUM(Assumptions!$F$68:$F$70)*P11+ SUMPRODUCT(Assumptions!$F$62:$F$64,Assumptions!$F$68:$F$70)/SUM(Assumptions!$F$68:$F$70)*P14) | R37: payment processing websites
D39: Salaries | M39: =SUM(M40:M42) | N39: =SUM(N40:N42) | O39: =SUM(O40:O42) | P39: =SUM(P40:P42) | Y39: =60*1.15
D40: Founder (1*3.5k EUR net/month) | E40: Gross/year | M40: =-Salaries!D3 | N40: =-Salaries!E3 | O40: =-Salaries!F3 | P40: =-Salaries!G3 | R40: Including taxes and social insurance
D41: Customer service (1*2500 EUR net/month) | E41: Gross/year | N41: =-Salaries!E10 | O41: =-Salaries!F10 | P41: =-Salaries!G10
D42: Designer (part time EUR net/month) | E42: Gross/year | N42: =-Salaries!E17 | O42: =-Salaries!F17 | P42: =-Salaries!G17
D44: Marketing | M44: =-M45*M27 | N44: =-N45*N27 | O44: =-O45*O27 | P44: =P45*P27
D45: Marketing % (of revenue) | M45: 0.1 | N45: 0.1 | O45: 0.07 | P45: 0.05 | R45: industry benchmark
D46: Cost of free samples | E46: 0.2 | M46: =M$44*$E46 | N46: =N$44*$E46 | O46: =O$44*$E46 | P46: =P$44*$E46
D47: Paid ads | E47: 0.8 | M47: =M$44*$E47 | N47: =N$44*$E47 | O47: =O$44*$E47 | P47: =P$44*$E47
D49: Design cost | M49: =M51 | N49: =N51 | O49: =O51 | P49: =P51
D50: Number of templates per year | M50: 16 | N50: 16 | O50: 16 | P50: 16
D51: Design templates cost | M51: =-M50*Assumptions!$F$76 | N51: =-N50*Assumptions!$F$76 | O51: =-O50*Assumptions!$F$76 | P51: =-P50*Assumptions!$F$76
D53: Operations | M53: =M54 | N53: =N54 | O53: =O54 | P53: =P54
D54: IT support (hosting, licences, etc.) | M54: -500 | N54: =M54 | O54: =N54 | P54: =O54
D55: API fee | M55: -1100 | R55: updated 31.07.2026
D57: Corporate overhead | M57: =SUM(M58:M60) | N57: =SUM(N58:N60) | O57: =SUM(O58:O60) | P57: =SUM(P58:P60)
D58: Company registration | M58: -300 | R58: estimation
D59: Trademark registration | M59: -250 | R59: estimation
D60: Accountant | M60: -1800 | N60: =M60 | O60: =N60 | P60: =O60 | R60: estimation
D62: Depreciation | M62: =M64 | N62: =N64 | O62: =O64 | P62: =P64
D63: Years of depreciation | E63: 3 | R63: simplified
M64: =M76/3 | N64: =M64+N76/3 | O64: =N64+O76/3 | P64: =N76/3+O76/3+P76/3
D66: Total OPEX (without contingency) | M66: =M57+M39+M53+M49+M44+M31+M62 | N66: =N57+N39+N53+N49+N44+N31+N62 | O66: =O57+O39+O53+O49+O44+O31+O62 | P66: =P57+P39+P53+P49+P44+P31+P62
D68: Contingency rate | M68: 0.05 | N68: =M68 | O68: =N68 | P68: =O68
D69: Contingency budget | M69: =M66*M68 | N69: =N66*N68 | O69: =O66*O68 | P69: =P66*P68
D71: Total OPEX | M71: =M66+M69 | N71: =N66+N69 | O71: =O66+O69 | P71: =P66+P69
B74: 3 | D74: CAPEX | M74: =M76 | N74: =N76 | O74: =O76 | P74: =P76
D76: Platform development | M76: -1000
D78: Total costs | M78: =M66+M69 | N78: =N66+N69 | O78: =O66+O69 | P78: =P66+P69
B81: 4 | D81: Margin
D83: Gross profit | M83: =M11+M31 | N83: =N11+N31 | O83: =O11+O31 | P83: =P11+P31
D84: Gross margin | M84: =M83/M11 | N84: =N83/N11 | O84: =O83/O11 | P84: =P83/P11
D85: EBIT | M85: =M11+M71 | N85: =N11+N71 | O85: =O11+O71 | P85: =P11+P71
D86: Operating margin | M86: =M85/M11 | N86: =N85/N11 | O86: =O85/O11 | P86: =P85/P11
B88: 5 | D88: Taxes
R89: Tax rates (appr.)
D90: CIT (income tax) | M90: =IF(M85>0,M85*$R$90,500) | N90: =IF(N85>0,N85*$R$90,500) | O90: =IF(O85>0,O85*$R$90,500) | P90: =IF(P85>0,P85*$R$90,500) | R90: 0.23
D91: NOPAT (Net operating profit after tax) | M91: =M85-M90 | N91: =N85-N90 | O91: =O85-O90 | P91: =P85-P90
D92: Divident tax | M92: =IF(M91>0,M91*$R$92,0) | N92: =IF(N91>0,N91*$R$92,0) | O92: =IF(O91>0,O91*$R$92,0) | P92: =IF(P91>0,P91*$R$92,0) | R92: 0.275
B94: 6 | D94: Net income / dividents | M94: =M91-M92 | N94: =N91-N92 | O94: =O91-O92 | P94: =P91-P92
B96: 7 | D96: Cash flow
D98: FCF | M98: =M85-M64+M76 | N98: =N85-N64+N76 | O98: =O85-O64+O76 | P98: =P85-P64+P76
D99: WACC | M99: 0.08
D100: NPV | M100: =NPV(M99,N98:P98)+M98

Sheet Business case - Quarterly view
D2: hard input
D3: link to Assumptions tab
D4: calc
D5: not used for calcs
D6: Printing provider | F6: Printsmarter
D7: Provider index (1=Printsmarter, 2=Elanders) | F7: =IF($F$6="Elanders",2,1)
G8: 2026 | H8: 2026 | I8: 2026 | J8: 2026 | K8: 2027 | L8: 2027 | M8: 2027 | N8: 2027 | O8: 2028 | P8: 2028 | Q8: 2028 | R8: 2028
B9: # | D9: Metric | E9: Unit | G9: 1Q 2026 | H9: 2Q 2026 | I9: 3Q 2026 | J9: 4Q 2026 | K9: 1Q 2027 | L9: 2Q 2027 | M9: 3Q 2027 | N9: 4Q2027 | O9: 1Q 2028 | P9: 2Q 2028 | Q9: 3Q 2028 | R9: 4Q2028 | T9: Comments
B11: 1 | D11: Revenue | G11: =G34 | H11: =H34 | I11: =I34 | J11: =J34 | K11: =K34 | L11: =L34 | M11: =M34 | N11: =N34 | ... R11: =R34
D13: Number of orders per day | G13: =Marketing!G33 | H13: =Marketing!H33 | I13: =Marketing!I33 | J13: =Marketing!J33 | K13: =Marketing!K33 | L13: =Marketing!L33 | M13: =Marketing!M33 | N13: =Marketing!N33 | ... R13: =Marketing!R33 | T13: Driven by Marketing tab (was hard-typed).
D14: Number of orders per month | G14: 0 | H14: 0 | I14: 0 | J14: =J13*30 | K14: =K13*30 | L14: =L13*30 | M14: =M13*30 | N14: =N13*30 | O14: =O13*30 | P14: =P13*30 | Q14: =Q13*30 | R14: =R13*30
D15: Number of orders per quarter | G15: 0 | H15: 0 | I15: 0 | J15: =J14*3 | K15: =K14*3 | L15: =L14*3 | M15: =M14*3 | N15: =N14*3 | O15: =O14*3 | P15: =P14*3 | Q15: =Q14*3 | R15: =R14*3
D17: B2C | E17: # orders | G17: =ROUND(IF(G15-G18<=0,0,G15-G18),0) | H17: =ROUND(IF(H15-H18<=0,0,H15-H18),0) | I17: =ROUND(IF(I15-I18<=0,0,I15-I18),0) | J17: =ROUND(IF(J15-J18<=0,0,J15-J18),0) | K17: =ROUND(IF(K15-K18<=0,0,K15-K18),0) | L17: =ROUND(IF(L15-L18<=0,0,L15-L18),0) | M17: =ROUND(IF(M15-M18<=0,0,M15-M18),0) | N17: =ROUND(IF(N15-N18<=0,0,N15-N18),0) | ... R17: =ROUND(IF(R15-R18<=0,0,R15-R18),0)
D18: B2B | E18: # orders | G18: {=G15*INDEX(Assumptions!$F$84:$I$84,,MATCH(G$8,Assumptions!$F$82:$I$82))} | H18: {=H15*INDEX(Assumptions!$F$84:$I$84,,MATCH(H$8,Assumptions!$F$82:$I$82))} | I18: {=I15*INDEX(Assumptions!$F$84:$I$84,,MATCH(I$8,Assumptions!$F$82:$I$82))} | J18: {=J15*INDEX(Assumptions!$F$84:$I$84,,MATCH(J$8,Assumptions!$F$82:$I$82))} | K18: {=K15*INDEX(Assumptions!$F$84:$I$84,,MATCH(K$8,Assumptions!$F$82:$I$82))} | L18: {=L15*INDEX(Assumptions!$F$84:$I$84,,MATCH(L$8,Assumptions!$F$82:$I$82))} | M18: {=M15*INDEX(Assumptions!$F$84:$I$84,,MATCH(M$8,Assumptions!$F$82:$I$82))} | N18: {=N15*INDEX(Assumptions!$F$84:$I$84,,MATCH(N$8,Assumptions!$F$82:$I$82))} | ... R18: {=R15*INDEX(Assumptions!$F$84:$I$84,,MATCH(R$8,Assumptions!$F$82:$I$82))}
D20: Share of 40-page books | E20: % | G20: 0.8 | H20: =G20 | I20: 0.8 | J20: 0.8 | K20: 0.8 | L20: 0.7 | M20: 0.7 | N20: 0.7 | O20: 0.6 | P20: 0.6 | Q20: 0.6 | R20: 0.6
D21: Share of 80-page books | E21: % | G21: =1-G20 | H21: =1-H20 | I21: =1-I20 | J21: =1-J20 | K21: =1-K20 | L21: =1-L20 | M21: =1-M20 | N21: =1-N20 | ... R21: =1-R20
D23: Price 40-page book (excl. VAT) | E23: EUR | G23: =G24/(1+Assumptions!$F$12) | H23: =H24/(1+Assumptions!$F$12) | I23: =I24/(1+Assumptions!$F$12) | J23: =J24/(1+Assumptions!$F$12) | K23: =K24/(1+Assumptions!$F$12) | L23: =L24/(1+Assumptions!$F$12) | M23: =M24/(1+Assumptions!$F$12) | N23: =N24/(1+Assumptions!$F$12) | ... R23: =R24/(1+Assumptions!$F$12)
D24: Price 40-page book (incl. VAT) | E24: EUR | G24: 70 | H24: =G24 | I24: =H24 | J24: =I24 | K24: =J24 | L24: =K24 | M24: =L24 | N24: =M24 | O24: =N24 | ... R24: =Q24
D25: Price 80-page book (excl. VAT) | E25: EUR | G25: =G26/(1+Assumptions!$F$12) | H25: =H26/(1+Assumptions!$F$12) | I25: =I26/(1+Assumptions!$F$12) | J25: =J26/(1+Assumptions!$F$12) | K25: =K26/(1+Assumptions!$F$12) | L25: =L26/(1+Assumptions!$F$12) | M25: =M26/(1+Assumptions!$F$12) | N25: =N26/(1+Assumptions!$F$12) | ... R25: =R26/(1+Assumptions!$F$12)
D26: Price 80-page book (incl. VAT) | E26: EUR | G26: 100 | H26: =G26 | I26: =H26 | J26: =I26 | K26: =J26 | L26: =K26 | M26: =L26 | N26: =M26 | O26: =N26 | ... R26: =Q26
D29: Average check B2C (excl VAT) | E29: EUR | G29: =G23*G20+G25*G21 | H29: =H23*H20+H25*H21 | I29: =I23*I20+I25*I21 | J29: =J23*J20+J25*J21 | K29: =K23*K20+K25*K21 | L29: =L23*L20+L25*L21 | M29: =M23*M20+M25*M21 | N29: =N23*N20+N25*N21 | ... R29: =R23*R20+R25*R21
D30: Average check B2C (with VAT) | E30: EUR | G30: =G29*(1+Assumptions!$F$12) | H30: =H29*(1+Assumptions!$F$12) | I30: =I29*(1+Assumptions!$F$12) | J30: =J29*(1+Assumptions!$F$12) | K30: =K29*(1+Assumptions!$F$12) | L30: =L29*(1+Assumptions!$F$12) | M30: =M29*(1+Assumptions!$F$12) | N30: =N29*(1+Assumptions!$F$12) | ... R30: =R29*(1+Assumptions!$F$12)
D31: Average check B2B (excl VAT) | E31: EUR | G31: 0 | H31: 0 | I31: 0 | J31: {=J29*(1+INDEX(Assumptions!$F$83:$I$83,,MATCH(J$8,Assumptions!$F$82:$I$82)))} | K31: {=K29*(1+INDEX(Assumptions!$F$83:$I$83,,MATCH(K$8,Assumptions!$F$82:$I$82)))} | L31: {=L29*(1+INDEX(Assumptions!$F$83:$I$83,,MATCH(L$8,Assumptions!$F$82:$I$82)))} | M31: {=M29*(1+INDEX(Assumptions!$F$83:$I$83,,MATCH(M$8,Assumptions!$F$82:$I$82)))} | N31: {=N29*(1+INDEX(Assumptions!$F$83:$I$83,,MATCH(N$8,Assumptions!$F$82:$I$82)))} | O31: {=O29*(1+INDEX(Assumptions!$F$83:$I$83,,MATCH(O$8,Assumptions!$F$82:$I$82)))} | P31: {=P29*(1+INDEX(Assumptions!$F$83:$I$83,,MATCH(P$8,Assumptions!$F$82:$I$82)))} | Q31: {=Q29*(1+INDEX(Assumptions!$F$83:$I$83,,MATCH(Q$8,Assumptions!$F$82:$I$82)))} | R31: {=R29*(1+INDEX(Assumptions!$F$83:$I$83,,MATCH(R$8,Assumptions!$F$82:$I$82)))}
D32: Average check B2B (with VAT) | E32: EUR | G32: =G31*(1+Assumptions!$F$12) | H32: =H31*(1+Assumptions!$F$12) | I32: =I31*(1+Assumptions!$F$12) | J32: =J31*(1+Assumptions!$F$12) | K32: =K31*(1+Assumptions!$F$12) | L32: =L31*(1+Assumptions!$F$12) | M32: =M31*(1+Assumptions!$F$12) | N32: =N31*(1+Assumptions!$F$12) | ... R32: =R31*(1+Assumptions!$F$12)
D34: Sales | I34: =I35+I36 | J34: =J35+J36 | K34: =K35+K36 | L34: =L35+L36 | M34: =M35+M36 | N34: =N35+N36 | O34: =O35+O36 | P34: =P35+P36 | ... R34: =R35+R36
D35: B2C | E35: EUR | I35: =I17*I29 | J35: =J17*J29 | K35: =K17*K29 | L35: =L17*L29 | M35: =M17*M29 | N35: =N17*N29 | O35: =O17*O29 | P35: =P17*P29 | ... R35: =R17*R29
D36: B2B | E36: EUR | I36: =I18*I30 | J36: =J18*J30 | K36: =K18*K30 | L36: =L18*L30 | M36: =M18*M30 | N36: =N18*N30 | O36: =O18*O30 | P36: =P18*P30 | ... R36: =R18*R30
D37: Defect % | I37: 0 | J37: =I37 | K37: =J37 | L37: =K37 | M37: =L37 | N37: =M37 | O37: =N37 | P37: =O37 | Q37: =P37 | R37: =Q37 | T37: Assumed as 0% as printing provider will pay for any defect
D38: Net sales | I38: =I34*(1-I37) | J38: =J34*(1-J37) | K38: =K34*(1-K37) | L38: =L34*(1-L37) | M38: =M34*(1-M37) | N38: =N34*(1-N37) | O38: =O34*(1-O37) | P38: =P34*(1-P37) | ... R38: =R34*(1-R37)
D40: 2nd Engine Revenue | E40: EUR | G40: 23100 | H40: 18000 | I40: 12000 | J40: 12000 | T40: Consulting revenue (not related to aevia)
B43: 2 | D43: OPEX
D46: Share of AT deliveries | E46: % | I46: 1 | J46: 1 | K46: 1 | L46: 1 | M46: 1 | N46: 1 | O46: 0.95 | P46: 0.9 | Q46: 0.8 | R46: 0.7 | T46: Dummy
D47: Volume tier (Assumptions col #) | I47: =IFERROR(MATCH(I$13,Assumptions!$F$20:$N$20,1),1) | J47: =IFERROR(MATCH(J$13,Assumptions!$F$20:$N$20,1),1) | K47: =IFERROR(MATCH(K$13,Assumptions!$F$20:$N$20,1),1) | L47: =IFERROR(MATCH(L$13,Assumptions!$F$20:$N$20,1),1) | M47: =IFERROR(MATCH(M$13,Assumptions!$F$20:$N$20,1),1) | N47: =IFERROR(MATCH(N$13,Assumptions!$F$20:$N$20,1),1) | O47: =IFERROR(MATCH(O$13,Assumptions!$F$20:$N$20,1),1) | P47: =IFERROR(MATCH(P$13,Assumptions!$F$20:$N$20,1),1) | ... R47: =IFERROR(MATCH(R$13,Assumptions!$F$20:$N$20,1),1)
D49: COGS | G49: 0 | H49: 0 | I49: =SUM(I50:I55) | J49: =SUM(J50:J55) | K49: =SUM(K50:K55) | L49: =SUM(L50:L55) | M49: =SUM(M50:M55) | N49: =SUM(N50:N55) | O49: =SUM(O50:O55) | P49: =SUM(P50:P55) | ... R49: =SUM(R50:R55)
D50: Printing | G50: 0 | H50: 0 | I50: {=-IFERROR((INDEX(CHOOSE($F$7,Assumptions!$F$24:$N$24,Assumptions!$F$37:$N$37),1,I$47)*(1-I$21)+INDEX(CHOOSE($F$7,Assumptions!$F$25:$N$25,Assumptions!$F$38:$N$38),1,I$47)*I$21)*I$15,0)} | J50: {=-IFERROR((INDEX(CHOOSE($F$7,Assumptions!$F$24:$N$24,Assumptions!$F$37:$N$37),1,J$47)*(1-J$21)+INDEX(CHOOSE($F$7,Assumptions!$F$25:$N$25,Assumptions!$F$38:$N$38),1,J$47)*J$21)*J$15,0)} | K50: {=-IFERROR((INDEX(CHOOSE($F$7,Assumptions!$F$24:$N$24,Assumptions!$F$37:$N$37),1,K$47)*(1-K$21)+INDEX(CHOOSE($F$7,Assumptions!$F$25:$N$25,Assumptions!$F$38:$N$38),1,K$47)*K$21)*K$15,0)} | L50: {=-IFERROR((INDEX(CHOOSE($F$7,Assumptions!$F$24:$N$24,Assumptions!$F$37:$N$37),1,L$47)*(1-L$21)+INDEX(CHOOSE($F$7,Assumptions!$F$25:$N$25,Assumptions!$F$38:$N$38),1,L$47)*L$21)*L$15,0)} | M50: {=-IFERROR((INDEX(CHOOSE($F$7,Assumptions!$F$24:$N$24,Assumptions!$F$37:$N$37),1,M$47)*(1-M$21)+INDEX(CHOOSE($F$7,Assumptions!$F$25:$N$25,Assumptions!$F$38:$N$38),1,M$47)*M$21)*M$15,0)} | N50: {=-IFERROR((INDEX(CHOOSE($F$7,Assumptions!$F$24:$N$24,Assumptions!$F$37:$N$37),1,N$47)*(1-N$21)+INDEX(CHOOSE($F$7,Assumptions!$F$25:$N$25,Assumptions!$F$38:$N$38),1,N$47)*N$21)*N$15,0)} | O50: {=-IFERROR((INDEX(CHOOSE($F$7,Assumptions!$F$24:$N$24,Assumptions!$F$37:$N$37),1,O$47)*(1-O$21)+INDEX(CHOOSE($F$7,Assumptions!$F$25:$N$25,Assumptions!$F$38:$N$38),1,O$47)*O$21)*O$15,0)} | P50: {=-IFERROR((INDEX(CHOOSE($F$7,Assumptions!$F$24:$N$24,Assumptions!$F$37:$N$37),1,P$47)*(1-P$21)+INDEX(CHOOSE($F$7,Assumptions!$F$25:$N$25,Assumptions!$F$38:$N$38),1,P$47)*P$21)*P$15,0)} | ... R50: {=-IFERROR((INDEX(CHOOSE($F$7,Assumptions!$F$24:$N$24,Assumptions!$F$37:$N$37),1,R$47)*(1-R$21)+INDEX(CHOOSE($F$7,Assumptions!$F$25:$N$25,Assumptions!$F$38:$N$38),1,R$47)*R$21)*R$15,0)}
D51: Packaging | G51: 0 | H51: 0 | I51: {=-IFERROR(INDEX(CHOOSE($F$7,Assumptions!$F$26:$N$26,Assumptions!$F$39:$N$39),1,I$47)*I$15,0)} | J51: {=-IFERROR(INDEX(CHOOSE($F$7,Assumptions!$F$26:$N$26,Assumptions!$F$39:$N$39),1,J$47)*J$15,0)} | K51: {=-IFERROR(INDEX(CHOOSE($F$7,Assumptions!$F$26:$N$26,Assumptions!$F$39:$N$39),1,K$47)*K$15,0)} | L51: {=-IFERROR(INDEX(CHOOSE($F$7,Assumptions!$F$26:$N$26,Assumptions!$F$39:$N$39),1,L$47)*L$15,0)} | M51: {=-IFERROR(INDEX(CHOOSE($F$7,Assumptions!$F$26:$N$26,Assumptions!$F$39:$N$39),1,M$47)*M$15,0)} | N51: {=-IFERROR(INDEX(CHOOSE($F$7,Assumptions!$F$26:$N$26,Assumptions!$F$39:$N$39),1,N$47)*N$15,0)} | O51: {=-IFERROR(INDEX(CHOOSE($F$7,Assumptions!$F$26:$N$26,Assumptions!$F$39:$N$39),1,O$47)*O$15,0)} | P51: {=-IFERROR(INDEX(CHOOSE($F$7,Assumptions!$F$26:$N$26,Assumptions!$F$39:$N$39),1,P$47)*P$15,0)} | ... R51: {=-IFERROR(INDEX(CHOOSE($F$7,Assumptions!$F$26:$N$26,Assumptions!$F$39:$N$39),1,R$47)*R$15,0)}
D52: Cloud | G52: 0 | H52: 0 | I52: {=-IFERROR(INDEX(CHOOSE($F$7,Assumptions!$F$32:$N$32,Assumptions!$F$45:$N$45),1,I$47)*I$15,0)} | J52: {=-IFERROR(INDEX(CHOOSE($F$7,Assumptions!$F$32:$N$32,Assumptions!$F$45:$N$45),1,J$47)*J$15,0)} | K52: {=-IFERROR(INDEX(CHOOSE($F$7,Assumptions!$F$32:$N$32,Assumptions!$F$45:$N$45),1,K$47)*K$15,0)} | L52: {=-IFERROR(INDEX(CHOOSE($F$7,Assumptions!$F$32:$N$32,Assumptions!$F$45:$N$45),1,L$47)*L$15,0)} | M52: {=-IFERROR(INDEX(CHOOSE($F$7,Assumptions!$F$32:$N$32,Assumptions!$F$45:$N$45),1,M$47)*M$15,0)} | N52: {=-IFERROR(INDEX(CHOOSE($F$7,Assumptions!$F$32:$N$32,Assumptions!$F$45:$N$45),1,N$47)*N$15,0)} | O52: {=-IFERROR(INDEX(CHOOSE($F$7,Assumptions!$F$32:$N$32,Assumptions!$F$45:$N$45),1,O$47)*O$15,0)} | P52: {=-IFERROR(INDEX(CHOOSE($F$7,Assumptions!$F$32:$N$32,Assumptions!$F$45:$N$45),1,P$47)*P$15,0)} | ... R52: {=-IFERROR(INDEX(CHOOSE($F$7,Assumptions!$F$32:$N$32,Assumptions!$F$45:$N$45),1,R$47)*R$15,0)}
D53: Delivery | G53: 0 | H53: 0 | I53: =-IFERROR((INDEX(CHOOSE($F$7,Assumptions!$F$30:$N$30,Assumptions!$F$43:$N$43),1,I$47)*I$46+INDEX(CHOOSE($F$7,Assumptions!$F$31:$N$31,Assumptions!$F$44:$N$44),1,I$47)*(1-I$46))*I$15,0)+Assumptions!$F$114*I$15 | J53: =-IFERROR((INDEX(CHOOSE($F$7,Assumptions!$F$30:$N$30,Assumptions!$F$43:$N$43),1,J$47)*J$46+INDEX(CHOOSE($F$7,Assumptions!$F$31:$N$31,Assumptions!$F$44:$N$44),1,J$47)*(1-J$46))*J$15,0)+Assumptions!$F$114*J$15 | K53: =-IFERROR((INDEX(CHOOSE($F$7,Assumptions!$F$30:$N$30,Assumptions!$F$43:$N$43),1,K$47)*K$46+INDEX(CHOOSE($F$7,Assumptions!$F$31:$N$31,Assumptions!$F$44:$N$44),1,K$47)*(1-K$46))*K$15,0)+Assumptions!$F$114*K$15 | L53: =-IFERROR((INDEX(CHOOSE($F$7,Assumptions!$F$30:$N$30,Assumptions!$F$43:$N$43),1,L$47)*L$46+INDEX(CHOOSE($F$7,Assumptions!$F$31:$N$31,Assumptions!$F$44:$N$44),1,L$47)*(1-L$46))*L$15,0)+Assumptions!$F$114*L$15 | M53: =-IFERROR((INDEX(CHOOSE($F$7,Assumptions!$F$30:$N$30,Assumptions!$F$43:$N$43),1,M$47)*M$46+INDEX(CHOOSE($F$7,Assumptions!$F$31:$N$31,Assumptions!$F$44:$N$44),1,M$47)*(1-M$46))*M$15,0)+Assumptions!$F$114*M$15 | N53: =-IFERROR((INDEX(CHOOSE($F$7,Assumptions!$F$30:$N$30,Assumptions!$F$43:$N$43),1,N$47)*N$46+INDEX(CHOOSE($F$7,Assumptions!$F$31:$N$31,Assumptions!$F$44:$N$44),1,N$47)*(1-N$46))*N$15,0)+Assumptions!$F$114*N$15 | O53: =-IFERROR((INDEX(CHOOSE($F$7,Assumptions!$F$30:$N$30,Assumptions!$F$43:$N$43),1,O$47)*O$46+INDEX(CHOOSE($F$7,Assumptions!$F$31:$N$31,Assumptions!$F$44:$N$44),1,O$47)*(1-O$46))*O$15,0)+Assumptions!$F$114*O$15 | P53: =-IFERROR((INDEX(CHOOSE($F$7,Assumptions!$F$30:$N$30,Assumptions!$F$43:$N$43),1,P$47)*P$46+INDEX(CHOOSE($F$7,Assumptions!$F$31:$N$31,Assumptions!$F$44:$N$44),1,P$47)*(1-P$46))*P$15,0)+Assumptions!$F$114*P$15 | ... R53: =-IFERROR((INDEX(CHOOSE($F$7,Assumptions!$F$30:$N$30,Assumptions!$F$43:$N$43),1,R$47)*R$46+INDEX(CHOOSE($F$7,Assumptions!$F$31:$N$31,Assumptions!$F$44:$N$44),1,R$47)*(1-R$46))*R$15,0)+Assumptions!$F$114*R$15 | T53: Net of customer-paid delivery (Assumptions F114). Carrier cost minus 4.99 charged.
D54: Royalty to artists | G54: 0 | H54: 0 | I54: =-I$34*I$63*Assumptions!$F$77 | J54: =-J$34*J$63*Assumptions!$F$77 | K54: =-K$34*K$63*Assumptions!$F$77 | L54: =-L$34*L$63*Assumptions!$F$77 | M54: =-M$34*M$63*Assumptions!$F$77 | N54: =-N$34*N$63*Assumptions!$F$77 | O54: =-O$34*O$63*Assumptions!$F$77 | P54: =-P$34*P$63*Assumptions!$F$77 | ... R54: =-R$34*R$63*Assumptions!$F$77
D55: Payment processing | G55: 0 | H55: 0 | J55: =-J34*Assumptions!$F$60 | K55: =-K34*Assumptions!$F$60 | L55: =-L34*Assumptions!$F$60 | M55: =-M34*Assumptions!$F$60 | N55: =-N34*Assumptions!$F$60 | O55: =-O34*Assumptions!$F$60 | P55: =-P34*Assumptions!$F$60 | Q55: =-Q34*Assumptions!$F$60 | R55: =-R34*Assumptions!$F$60
D58: Design costs | H58: -3000 | I58: -400 | J58: =J$60*J$64 | K58: =K$60*K$64 | L58: =L$60*L$64 | M58: =M$60*M$64 | N58: =N$60*N$64 | O58: =O$60*O$64 | P58: =P$60*P$64 | Q58: =Q$60*Q$64 | R58: =R$60*R$64
D59: Number of templates (cum) | H59: 7 | I59: 8 | J59: 9 | K59: 10 | L59: =K59+2 | M59: =L59+2 | N59: =M59+2 | O59: =N59+2 | P59: =O59+2 | Q59: =P59+2 | R59: =Q59+2
D60: Number of templates (new) | I60: =I59-H59 | J60: =J59-I59 | K60: =K59-J59 | L60: =L59-K59 | M60: =M59-L59 | N60: =N59-M59 | O60: =O59-N59 | P60: =P59-O59 | ... R60: =R59-Q59
D61: # of templates with royalty model (cum) | I61: 1 | J61: 1 | K61: 2 | L61: =K61+(L59-K59) | M61: =L61+(M59-L59) | N61: =M61+(N59-M59) | O61: =N61+(O59-N59) | P61: =O61+(P59-O59) | Q61: =P61+(Q59-P59) | R61: =Q61+(R59-Q59)
D62: # of templates with royalty model (new) | I62: =I61 | J62: =J61-I61 | K62: =K61-J61 | L62: =L61-K61 | M62: =M61-L61 | N62: =N61-M61 | O62: =O61-N61 | P62: =P61-O61 | Q62: =Q61-P61 | R62: =R61-Q61
D63: Share of templates with royalty model | I63: =I61/I59 | J63: =J61/J59 | K63: =K61/K59 | L63: =L61/L59 | M63: =M61/M59 | N63: =N61/N59 | O63: =O61/O59 | P63: =P61/P59 | ... R63: =R61/R59
D64: Average cost per template | I64: =(I58+H58)/I59 | J64: =I$64 | K64: =-Assumptions!$F$76 | L64: =-Assumptions!$F$76 | M64: =-Assumptions!$F$76 | N64: =-Assumptions!$F$76 | O64: =-Assumptions!$F$76 | P64: =-Assumptions!$F$76 | Q64: =-Assumptions!$F$76 | R64: =-Assumptions!$F$76
D66: Operations | G66: =G67+G68 | H66: =H67+H68 | I66: =I67+I68 | J66: =J67+J68 | K66: =K67+K68 | L66: =L67+L68 | M66: =M67+M68 | N66: =N67+N68 | ... R66: =R67+R68
D67: IT Licenses&Subscrtiptions | E67: EUR | G67: -268 | H67: -376 | I67: -400 | J67: -500 | K67: =J67 | L67: -800 | M67: =L67 | N67: =M67 | O67: -1000 | P67: =O67 | Q67: =P67 | R67: =Q67 | T67: rough estimations, considering a lot of things would be automazed and AI costs might grow
D68: API fee | E68: EUR | I68: -1100
D70: Corporate overhead | G70: =SUM(G71:G77) | H70: =SUM(H71:H77) | I70: =SUM(I71:I77) | J70: =SUM(J71:J77) | K70: =SUM(K71:K77) | L70: =SUM(L71:L77) | M70: =SUM(M71:M77) | N70: =SUM(N71:N77) | ... R70: =SUM(R71:R77)
D71: Company registration | E71: EUR | I71: 0 | J71: -300
D72: Trademark registration | E72: EUR | H72: -225
D73: Accountant | E73: EUR | H73: -295.2 | I73: -1231 | J73: -250 | K73: -250 | L73: -250 | M73: -1500 | N73: -250 | O73: -250 | P73: -250
D74: Business address | E74: EUR | G74: =-720/4 | H74: =-720/4 | I74: =-720/4 | J74: =-720/4 | K74: =J74 | L74: =K74 | M74: =L74 | N74: =M74 | O74: =N74 | P74: =O74 | Q74: =P74 | R74: =Q74
D75: Office rent | E75: EUR | H75: -492 | I75: -150 | J75: 0 | K75: 0 | L75: -600 | M75: 0 | N75: 0 | O75: 0 | P75: 0 | Q75: 0 | R75: 0
D76: Legal fees | E76: EUR | H76: -132
D77: Other | E77: EUR | H77: -65.8
D79: Salaries and social contributions | I79: =SUM(I80:I81) | J79: =SUM(J80:J81) | K79: =SUM(K80:K81) | L79: =SUM(L80:L81) | M79: =SUM(M80:M81) | N79: =SUM(N80:N81) | O79: =SUM(O80:O81) | P79: =SUM(P80:P81) | ... R79: =SUM(R80:R81)
D80: Designer (part time/freelance) | E80: EUR | O80: 0 | P80: 0 | Q80: 0 | R80: 0 | T80: Deferred — cannot afford pre-scale (S148). Re-add when volume justifies.
D81: SVS | E81: EUR | I81: =SUMIF('Tax & Founder income'!$F$5:$H$5,I$8,'Tax & Founder income'!$F$28:$H$28)/COUNTIF($I$8:$R$8,I$8) | J81: =SUMIF('Tax & Founder income'!$F$5:$H$5,J$8,'Tax & Founder income'!$F$28:$H$28)/COUNTIF($I$8:$R$8,J$8) | K81: =SUMIF('Tax & Founder income'!$F$5:$H$5,K$8,'Tax & Founder income'!$F$28:$H$28)/COUNTIF($I$8:$R$8,K$8) | L81: =SUMIF('Tax & Founder income'!$F$5:$H$5,L$8,'Tax & Founder income'!$F$28:$H$28)/COUNTIF($I$8:$R$8,L$8) | M81: =SUMIF('Tax & Founder income'!$F$5:$H$5,M$8,'Tax & Founder income'!$F$28:$H$28)/COUNTIF($I$8:$R$8,M$8) | N81: =SUMIF('Tax & Founder income'!$F$5:$H$5,N$8,'Tax & Founder income'!$F$28:$H$28)/COUNTIF($I$8:$R$8,N$8) | O81: =SUMIF('Tax & Founder income'!$F$5:$H$5,O$8,'Tax & Founder income'!$F$28:$H$28)/COUNTIF($I$8:$R$8,O$8) | P81: =SUMIF('Tax & Founder income'!$F$5:$H$5,P$8,'Tax & Founder income'!$F$28:$H$28)/COUNTIF($I$8:$R$8,P$8) | ... R81: =SUMIF('Tax & Founder income'!$F$5:$H$5,R$8,'Tax & Founder income'!$F$28:$H$28)/COUNTIF($I$8:$R$8,R$8)
D84: Marketing | E84: EUR | G84: =-Marketing!G37 | H84: =-Marketing!H37 | I84: =-Marketing!I37 | J84: =-Marketing!J37 | K84: =-Marketing!K37 | L84: =-Marketing!L37 | M84: =-Marketing!M37 | N84: =-Marketing!N37 | ... R84: =-Marketing!R37 | T84: Paid + referral rewards + content tools, from Marketing tab.
D92: Total OPEX (without contingency) | G92: =G49+G58+G66+G70+G79+G84 | H92: =H49+H58+H66+H70+H79+H84 | I92: =I49+I58+I66+I70+I79+I84 | J92: =J49+J58+J66+J70+J79+J84 | K92: =K49+K58+K66+K70+K79+K84 | L92: =L49+L58+L66+L70+L79+L84 | M92: =M49+M58+M66+M70+M79+M84 | N92: =N49+N58+N66+N70+N79+N84 | ... R92: =R49+R58+R66+R70+R79+R84
D94: Contingency rate | I94: 0.05 | J94: =I94 | K94: =J94 | L94: =K94 | M94: =L94 | N94: =M94 | O94: =N94 | P94: =O94 | Q94: =P94 | R94: =Q94
D95: Contingency budget | I95: =I94*I92 | J95: =J94*J92 | K95: =K94*K92 | L95: =L94*L92 | M95: =M94*M92 | N95: =N94*N92 | O95: =O94*O92 | P95: =P94*P92 | ... R95: =R94*R92
D97: Total OPEX | I97: =I92+I95 | J97: =J92+J95 | K97: =K92+K95 | L97: =L92+L95 | M97: =M92+M95 | N97: =N92+N95 | O97: =O92+O95 | P97: =P92+P95 | ... R97: =R92+R95
B100: 3 | D100: CAPEX | I100: =I102 | J100: =J102 | K100: =K102 | L100: =L102 | M100: =M102 | N100: =N102 | O100: =O102 | P100: =P102 | ... R100: =R102
D102: Platform development | I102: 0 | J102: =I102 | K102: =J102 | L102: =K102 | M102: =L102 | N102: =M102 | O102: =N102 | P102: =O102 | Q102: =P102 | R102: =Q102
B104: 4 | D104: Margin
D106: Gross profit | G106: =G11+G49 | H106: =H11+H49 | I106: =I11+I49 | J106: =J11+J49 | K106: =K11+K49 | L106: =L11+L49 | M106: =M11+M49 | N106: =N11+N49 | ... R106: =R11+R49
D107: Gross margin | G107: =IFERROR(G106/G11,"") | H107: =IFERROR(H106/H11,"") | I107: =IFERROR(I106/I11,"") | J107: =IFERROR(J106/J11,"") | K107: =IFERROR(K106/K11,"") | L107: =IFERROR(L106/L11,"") | M107: =IFERROR(M106/M11,"") | N107: =IFERROR(N106/N11,"") | ... R107: =IFERROR(R106/R11,"")
D108: EBIT | G108: =G97+G11 | H108: =H97+H11 | I108: =I97+I11 | J108: =J97+J11 | K108: =K97+K11 | L108: =L97+L11 | M108: =M97+M11 | N108: =N97+N11 | ... R108: =R97+R11
D109: Operating margin | G109: =IFERROR(G108/G11,"") | H109: =IFERROR(H108/H11,"") | I109: =IFERROR(I108/I11,"") | J109: =IFERROR(J108/J11,"") | K109: =IFERROR(K108/K11,"") | L109: =IFERROR(L108/L11,"") | M109: =IFERROR(M108/M11,"") | N109: =IFERROR(N108/N11,"") | ... R109: =IFERROR(R108/R11,"")

Sheet Marketing
D2: Marketing calculator — drives order volume & spend into the Quarterly view
D4: Yellow-ish = inputs you flex · others are formulas. Columns match the Quarterly view 1:1.
D8: Year | G8: 2026 | H8: 2026 | I8: 2026 | J8: 2026 | K8: 2027 | L8: 2027 | M8: 2027 | N8: 2027 | O8: 2028 | P8: 2028 | Q8: 2028 | R8: 2028
B9: # | D9: Metric | E9: Unit | G9: 1Q 2026 | H9: 2Q 2026 | I9: 3Q 2026 | J9: 4Q 2026 | K9: 1Q 2027 | L9: 2Q 2027 | M9: 3Q 2027 | N9: 4Q2027 | O9: 1Q 2028 | P9: 2Q 2028 | Q9: 3Q 2028 | R9: 4Q2028 | T9: Comments
B11: 1 | D11: Paid engine
D12: Quarterly paid budget | E12: EUR | G12: 0 | H12: 0 | I12: 0 | J12: 1500 | K12: 2000 | L12: 2500 | M12: 3000 | N12: 3500 | O12: 4000 | P12: 5000 | Q12: 6000 | R12: 7000 | T12: INPUT. Promo test lives here — start small, read the real CAC.
D13: CPC | E13: EUR | G13: 0.85 | H13: 0.85 | I13: 0.85 | J13: 0.85 | K13: 0.85 | L13: 0.85 | M13: 0.85 | N13: 0.85 | O13: 0.85 | P13: 0.85 | Q13: 0.85 | R13: 0.85 | T13: INPUT. Cost per click (Meta/IG). US-skewed guess until measured.
D14: Conversion rate (click→order) | E14: % | G14: 0.02 | H14: 0.02 | I14: 0.02 | J14: 0.02 | K14: 0.02 | L14: 0.02 | M14: 0.02 | N14: 0.02 | O14: 0.02 | P14: 0.02 | Q14: 0.02 | R14: 0.02 | T14: INPUT. 2% base per research; verify with the test.
D15: CAC override | E15: EUR | T15: INPUT (optional). Leave blank to use CPC÷conv. Fill once you MEASURE a real CAC — it then wins.
D16: Implied CAC (CPC ÷ conv) | E16: EUR | G16: =IF(G14>0,G13/G14,0) | H16: =IF(H14>0,H13/H14,0) | I16: =IF(I14>0,I13/I14,0) | J16: =IF(J14>0,J13/J14,0) | K16: =IF(K14>0,K13/K14,0) | L16: =IF(L14>0,L13/L14,0) | M16: =IF(M14>0,M13/M14,0) | N16: =IF(N14>0,N13/N14,0) | ... R16: =IF(R14>0,R13/R14,0)
D17: Effective CAC | E17: EUR | G17: =IF(G15<>"",G15,G16) | H17: =IF(H15<>"",H15,H16) | I17: =IF(I15<>"",I15,I16) | J17: =IF(J15<>"",J15,J16) | K17: =IF(K15<>"",K15,K16) | L17: =IF(L15<>"",L15,L16) | M17: =IF(M15<>"",M15,M16) | N17: =IF(N15<>"",N15,N16) | ... R17: =IF(R15<>"",R15,R16)
D18: Paid orders (quarter) | E18: pcs | G18: =IF(G17>0,ROUND(G12/G17,0),0) | H18: =IF(H17>0,ROUND(H12/H17,0),0) | I18: =IF(I17>0,ROUND(I12/I17,0),0) | J18: =IF(J17>0,ROUND(J12/J17,0),0) | K18: =IF(K17>0,ROUND(K12/K17,0),0) | L18: =IF(L17>0,ROUND(L12/L17,0),0) | M18: =IF(M17>0,ROUND(M12/M17,0),0) | N18: =IF(N17>0,ROUND(N12/N17,0),0) | ... R18: =IF(R17>0,ROUND(R12/R17,0),0)
B20: 2 | D20: Organic engine
D21: Organic orders (quarter) | E21: pcs | G21: 0 | H21: 0 | I21: 5 | J21: 10 | K21: 20 | L21: 30 | M21: 40 | N21: 50 | O21: 65 | P21: 80 | Q21: 95 | R21: 110 | T21: INPUT. Effort-capped ramp — cannot be bought. Set by content cadence, not budget.
D22: Content tools & production | E22: EUR/mo | G22: =G52 | H22: =H52 | I22: =I52 | J22: =J52 | K22: =K52 | L22: =L52 | M22: =M52 | N22: =N52 | ... R22: =R52 | T22: =breakdown below (row 52). Edit tools there, not here.
B24: 3 | D24: Referral engine
D25: Referral share of total orders | E25: % | G25: 0 | H25: 0 | I25: 0 | J25: 0.03 | K25: 0.04 | L25: 0.04 | M25: 0.05 | N25: 0.05 | O25: 0.06 | P25: 0.06 | Q25: 0.07 | R25: 0.07 | T25: INPUT. Referred orders as % of all orders (research: 3–5% yr0–1).
D26: Referral reward per referred order | E26: EUR | G26: 10 | H26: =G26 | I26: =H26 | J26: =I26 | K26: =J26 | L26: =K26 | M26: =L26 | N26: =M26 | O26: =N26 | ... R26: =Q26 | T26: INPUT. Only bites when share>0.
B28: 4 | D28: Outputs
D29: Paid orders | E29: pcs | G29: =G18 | H29: =H18 | I29: =I18 | J29: =J18 | K29: =K18 | L29: =L18 | M29: =M18 | N29: =N18 | ... R29: =R18
D30: Organic orders | E30: pcs | G30: =G21 | H30: =H21 | I30: =I21 | J30: =J21 | K30: =K21 | L30: =L21 | M30: =M21 | N30: =N21 | ... R30: =R21
D31: Acquired orders (quarter) | E31: pcs | G31: =IFERROR((G29+G30)/(1-G25),G29+G30) | H31: =IFERROR((H29+H30)/(1-H25),H29+H30) | I31: =IFERROR((I29+I30)/(1-I25),I29+I30) | J31: =IFERROR((J29+J30)/(1-J25),J29+J30) | K31: =IFERROR((K29+K30)/(1-K25),K29+K30) | L31: =IFERROR((L29+L30)/(1-L25),L29+L30) | M31: =IFERROR((M29+M30)/(1-M25),M29+M30) | N31: =IFERROR((N29+N30)/(1-N25),N29+N30) | ... R31: =IFERROR((R29+R30)/(1-R25),R29+R30)
D32: Referral orders (quarter) | E32: pcs | G32: =G25*G31 | H32: =H25*H31 | I32: =I25*I31 | J32: =J25*J31 | K32: =K25*K31 | L32: =L25*L31 | M32: =M25*M31 | N32: =N25*N31 | ... R32: =R25*R31
D33: Total orders per day (avg, incl. repeat) | E33: pcs/day | G33: =(G31+G34)/90 | H33: =(H31+H34)/90 | I33: =(I31+I34)/90 | J33: =(J31+J34)/90 | K33: =(K31+K34)/90 | L33: =(L31+L34)/90 | M33: =(M31+M34)/90 | N33: =(N31+N34)/90 | ... R33: =(R31+R34)/90 | T33: → feeds Quarterly row 13. Quarter ÷ 90 (30d × 3m).
D34: Repeat orders (quarter) | E34: pcs | G34: 0 | H34: 0 | I34: 0 | J34: 0 | K34: 0 | L34: 0 | M34: =$F$54*I31 | N34: =$F$54*J31 | O34: =$F$54*K31 | P34: =$F$54*L31 | Q34: =$F$54*M31 | R34: =$F$54*N31
D35: Acquisition spend (paid + referral) | E35: EUR | G35: =G12+G32*G26 | H35: =H12+H32*H26 | I35: =I12+I32*I26 | J35: =J12+J32*J26 | K35: =K12+K32*K26 | L35: =L12+L32*L26 | M35: =M12+M32*M26 | N35: =N12+N32*N26 | ... R35: =R12+R32*R26
D36: Content tools (quarter) | E36: EUR | G36: =G22*3 | H36: =H22*3 | I36: =I22*3 | J36: =J22*3 | K36: =K22*3 | L36: =L22*3 | M36: =M22*3 | N36: =N22*3 | ... R36: =R22*3
D37: Total marketing spend (quarter) | E37: EUR | G37: =G35+G36 | H37: =H35+H36 | I37: =I35+I36 | J37: =J35+J36 | K37: =K35+K36 | L37: =L35+L36 | M37: =M35+M36 | N37: =N35+N36 | ... R37: =R35+R36 | T37: → feeds Quarterly row 84 (as a negative OPEX).
D39: Blended CAC (excl. tools) | E39: EUR | G39: =IF(G31>0,G35/G31,0) | H39: =IF(H31>0,H35/H31,0) | I39: =IF(I31>0,I35/I31,0) | J39: =IF(J31>0,J35/J31,0) | K39: =IF(K31>0,K35/K31,0) | L39: =IF(L31>0,L35/L31,0) | M39: =IF(M31>0,M35/M31,0) | N39: =IF(N31>0,N35/N31,0) | ... R39: =IF(R31>0,R35/R31,0) | T39: Decision metric: acquisition spend ÷ total orders.
D40: Fully-loaded CAC (incl. tools) | E40: EUR | G40: =IF(G31>0,(G35+G36)/G31,0) | H40: =IF(H31>0,(H35+H36)/H31,0) | I40: =IF(I31>0,(I35+I36)/I31,0) | J40: =IF(J31>0,(J35+J36)/J31,0) | K40: =IF(K31>0,(K35+K36)/K31,0) | L40: =IF(L31>0,(L35+L36)/L31,0) | M40: =IF(M31>0,(M35+M36)/M31,0) | N40: =IF(N31>0,(N35+N36)/N31,0) | ... R40: =IF(R31>0,(R35+R36)/R31,0)
D44: Content tools breakdown (drives row 22)
D45: Tool | E45: EUR/mo | T45: What it's for
D46: Canva Pro | E46: EUR | G46: 0 | H46: 0 | I46: 12 | J46: 12 | K46: 12 | L46: 12 | M46: 12 | N46: 12 | O46: 12 | P46: 12 | Q46: 12 | R46: 12 | T46: Hub: layout, resizing, scheduling, Veo video
D47: Midjourney | E47: EUR | G47: 0 | H47: 0 | I47: 10 | J47: 10 | K47: 15 | L47: 15 | M47: 15 | N47: 15 | O47: 20 | P47: 20 | Q47: 20 | R47: 20 | T47: Editorial hero imagery (real assets, no fake people)
D48: CapCut Pro | E48: EUR | G48: 0 | H48: 0 | I48: 0 | J48: 0 | K48: 18 | L48: 18 | M48: 18 | N48: 18 | O48: 18 | P48: 18 | Q48: 18 | R48: 18 | T48: Reels / short-form video editing
D49: Video credits (Kling/Veo) | E49: EUR | G49: 0 | H49: 0 | I49: 28 | J49: 28 | K49: 25 | L49: 25 | M49: 25 | N49: 25 | O49: 50 | P49: 50 | Q49: 50 | R49: 50 | T49: Motion-video top-ups; scales as video grows
D50: Claude / ChatGPT | E50: EUR | G50: 0 | H50: 0 | I50: 0 | J50: 0 | K50: 0 | L50: 0 | M50: 0 | N50: 0 | O50: 0 | P50: 0 | Q50: 0 | R50: 0 | T50: Captions & copy — already owned, EUR 0
D51: Meta Business Suite | E51: EUR | G51: 0 | H51: 0 | I51: 0 | J51: 0 | K51: 0 | L51: 0 | M51: 0 | N51: 0 | O51: 0 | P51: 0 | Q51: 0 | R51: 0 | T51: Scheduling — free
D52: Total tools / month | E52: EUR | G52: =SUM(G46:G51) | H52: =SUM(H46:H51) | I52: =SUM(I46:I51) | J52: =SUM(J46:J51) | K52: =SUM(K46:K51) | L52: =SUM(L46:L51) | M52: =SUM(M46:M51) | N52: =SUM(N46:N51) | ... R52: =SUM(R46:R51)
D54: Repeat rate (~within 18 months) | F54: 0.2 | T54: Research ~20%. Applied with a ~12-month (4-quarter) lag; repeat orders carry NO CAC.

Sheet Sheet2
B2: Metric | C2: 2026 | D2: 2027 | E2: 2028
B3: Operating costs | C3: =SUM(C4:C8) | D3: =SUM(D4:D8) | E3: =SUM(E4:E8)
B4: COGS | C4: ='Business case - old'!M31 | D4: ='Business case - old'!N31 | E4: ='Business case - old'!O31
B5: Printing | C5: ='Business case - old'!M32 | D5: ='Business case - old'!N32 | E5: ='Business case - old'!O32
B6: Packaging & Delivery | C6: ='Business case - old'!M33+'Business case - old'!M35 | D6: ='Business case - old'!N33+'Business case - old'!N35 | E6: ='Business case - old'!O33+'Business case - old'!O35
B7: Artist royalty (2% of revenue) | C7: ='Business case - old'!M36 | D7: ='Business case - old'!N36 | E7: ='Business case - old'!O36
B8: Payment processing & Cloud | C8: ='Business case - old'!M37+'Business case - old'!M34 | D8: ='Business case - old'!N37+'Business case - old'!N34 | E8: ='Business case - old'!O37+'Business case - old'!O34
B9: Salaries | C9: =SUM(C10:C12) | D9: =SUM(D10:D12) | E9: =SUM(E10:E12)
B10: Net salary for Founders | C10: ='Business case - old'!M40 | D10: ='Business case - old'!N40 | E10: ='Business case - old'!O40
B11: Net salary for Customer service and Designer (contractor) | C11: ='Business case - old'!M41 | D11: ='Business case - old'!N41 | E11: ='Business case - old'!O41
B12: Social insurance & Wage tax | C12: ='Business case - old'!M42 | D12: ='Business case - old'!N42 | E12: ='Business case - old'!O42
B13: Marketing (5-10% of revenue) | C13: ='Business case - old'!M44 | D13: ='Business case - old'!N44 | E13: ='Business case - old'!O44
B14: Design cost (# templates per year = 16) | C14: ='Business case - old'!M49 | D14: ='Business case - old'!N49 | E14: ='Business case - old'!O49
B15: IT (hosting, licences, etc.) | C15: ='Business case - old'!M53 | D15: ='Business case - old'!N53 | E15: ='Business case - old'!O53
B16: Corporate overhead | C16: =SUM(C17:C19) | D16: =SUM(D17:D19) | E16: =SUM(E17:E19)
B17: Company registration | C17: ='Business case - old'!M58 | D17: ='Business case - old'!N58 | E17: ='Business case - old'!O58
B18: Trademark registration | C18: ='Business case - old'!M59 | D18: ='Business case - old'!N59 | E18: ='Business case - old'!O59
B19: Accountant | C19: ='Business case - old'!M60 | D19: ='Business case - old'!N60 | E19: ='Business case - old'!O60
B20: Contingency (5%) | C20: ='Business case - old'!M69 | D20: ='Business case - old'!N69 | E20: ='Business case - old'!O69

Sheet Tax & Founder income
B2: Founder income & Austrian tax (Einzelunternehmer)
D3: Sole trader: no salary. Business profit IS the taxable income. Only SVS contributions are deductible; income tax is private.
D5: Metric | E5: Unit | F5: 2026 | G5: 2027 | H5: 2028
D6: 2026 covers H2 only (Q3+Q4) - the model starts in 3Q 2026.
D8: 1. Operating result
D9: Net sales | E9: EUR | F9: =SUMIF('Business case - Quarterly view'!$I$8:$R$8,F$5,'Business case - Quarterly view'!$I$38:$R$38) | G9: =SUMIF('Business case - Quarterly view'!$I$8:$R$8,G$5,'Business case - Quarterly view'!$I$38:$R$38) | H9: =SUMIF('Business case - Quarterly view'!$I$8:$R$8,H$5,'Business case - Quarterly view'!$I$38:$R$38)
D10: COGS | E10: EUR | F10: =SUMIF('Business case - Quarterly view'!$I$8:$R$8,F$5,'Business case - Quarterly view'!$I$49:$R$49) | G10: =SUMIF('Business case - Quarterly view'!$I$8:$R$8,G$5,'Business case - Quarterly view'!$I$49:$R$49) | H10: =SUMIF('Business case - Quarterly view'!$I$8:$R$8,H$5,'Business case - Quarterly view'!$I$49:$R$49)
D11: Design costs | E11: EUR | F11: =SUMIF('Business case - Quarterly view'!$I$8:$R$8,F$5,'Business case - Quarterly view'!$I$58:$R$58) | G11: =SUMIF('Business case - Quarterly view'!$I$8:$R$8,G$5,'Business case - Quarterly view'!$I$58:$R$58) | H11: =SUMIF('Business case - Quarterly view'!$I$8:$R$8,H$5,'Business case - Quarterly view'!$I$58:$R$58)
D12: Operations | E12: EUR | F12: =SUMIF('Business case - Quarterly view'!$I$8:$R$8,F$5,'Business case - Quarterly view'!$I$66:$R$66) | G12: =SUMIF('Business case - Quarterly view'!$I$8:$R$8,G$5,'Business case - Quarterly view'!$I$66:$R$66) | H12: =SUMIF('Business case - Quarterly view'!$I$8:$R$8,H$5,'Business case - Quarterly view'!$I$66:$R$66)
D13: Corporate overhead | E13: EUR | F13: =SUMIF('Business case - Quarterly view'!$I$8:$R$8,F$5,'Business case - Quarterly view'!$I$70:$R$70) | G13: =SUMIF('Business case - Quarterly view'!$I$8:$R$8,G$5,'Business case - Quarterly view'!$I$70:$R$70) | H13: =SUMIF('Business case - Quarterly view'!$I$8:$R$8,H$5,'Business case - Quarterly view'!$I$70:$R$70)
D14: Freelancers (designer) | E14: EUR | F14: =SUMIF('Business case - Quarterly view'!$I$8:$R$8,F$5,'Business case - Quarterly view'!$I$80:$R$80) | G14: =SUMIF('Business case - Quarterly view'!$I$8:$R$8,G$5,'Business case - Quarterly view'!$I$80:$R$80) | H14: =SUMIF('Business case - Quarterly view'!$I$8:$R$8,H$5,'Business case - Quarterly view'!$I$80:$R$80)
D15: Marketing | E15: EUR | F15: =SUMIF('Business case - Quarterly view'!$I$8:$R$8,F$5,'Business case - Quarterly view'!$I$84:$R$84) | G15: =SUMIF('Business case - Quarterly view'!$I$8:$R$8,G$5,'Business case - Quarterly view'!$I$84:$R$84) | H15: =SUMIF('Business case - Quarterly view'!$I$8:$R$8,H$5,'Business case - Quarterly view'!$I$84:$R$84)
D16: Profit before SVS & tax | E16: EUR | F16: =SUM(F9:F15) | G16: =SUM(G9:G15) | H16: =SUM(H9:H15)
D18: 2. SVS social security contributions
D19: Months of SVS liability | E19: # | F19: 6 | G19: 12 | H19: 12
D20: Contribution base before floor/cap | E20: EUR | F20: =MAX(0,F16) | G20: =MAX(0,G16) | H20: =MAX(0,H16)
D21: Minimum base (period) | E21: EUR | F21: =Assumptions!$F$95*F$19 | G21: =Assumptions!$F$95*G$19 | H21: =Assumptions!$F$95*H$19
D22: Maximum base (period) | E22: EUR | F22: =Assumptions!$F$96*F$19 | G22: =Assumptions!$F$96*G$19 | H22: =Assumptions!$F$96*H$19
D23: Contribution base applied | E23: EUR | F23: =MIN(MAX(F20,F21),F22) | G23: =MIN(MAX(G20,G21),G22) | H23: =MIN(MAX(H20,H21),H22)
D24: Pension insurance (PV) | E24: EUR | F24: =-F23*Assumptions!$F$90 | G24: =-G23*Assumptions!$F$90 | H24: =-H23*Assumptions!$F$90
D25: Health insurance (KV) | E25: EUR | F25: =-F23*Assumptions!$F$91 | G25: =-G23*Assumptions!$F$91 | H25: =-H23*Assumptions!$F$91
D26: Self-employment provision | E26: EUR | F26: =-F23*Assumptions!$F$92 | G26: =-G23*Assumptions!$F$92 | H26: =-H23*Assumptions!$F$92
D27: Accident insurance (UV, flat) | E27: EUR | F27: =-Assumptions!$F$94*F$19 | G27: =-Assumptions!$F$94*G$19 | H27: =-Assumptions!$F$94*H$19
D28: Total SVS contributions | E28: EUR | F28: =SUM(F24:F27) | G28: =SUM(G24:G27) | H28: =SUM(H24:H27)
D30: 3. Income tax
D31: Profit after SVS (Gewinn) | E31: EUR | F31: =F16+F28 | G31: =G16+G28 | H31: =H16+H28
D32: Gewinnfreibetrag (Grundfreibetrag) | E32: EUR | F32: =-MIN(MAX(F31,0),Assumptions!$F$110)*Assumptions!$F$109 | G32: =-MIN(MAX(G31,0),Assumptions!$F$110)*Assumptions!$F$109 | H32: =-MIN(MAX(H31,0),Assumptions!$F$110)*Assumptions!$F$109
D33: Profit after Gewinnfreibetrag | E33: EUR | F33: =F31+F32 | G33: =G31+G32 | H33: =H31+H32
D34: Loss carry-forward - opening | E34: EUR | F34: 0 | G34: =F36 | H34: =G36
D35: Loss carry-forward used | E35: EUR | F35: =-MIN(MAX(F33,0)*Assumptions!$F$112,F34) | G35: =-MIN(MAX(G33,0)*Assumptions!$F$112,G34) | H35: =-MIN(MAX(H33,0)*Assumptions!$F$112,H34)
D36: Loss carry-forward - closing | E36: EUR | F36: =F34+F35+MAX(0,-F33) | G36: =G34+G35+MAX(0,-G33) | H36: =H34+H35+MAX(0,-H33)
D37: Taxable income | E37: EUR | F37: =MAX(0,F33+F35) | G37: =MAX(0,G33+G35) | H37: =MAX(0,H33+H35)
D39: Income tax, bracket by bracket
D40: =TEXT(Assumptions!$F100,"#,##0")&" - "&TEXT(Assumptions!$G100,"#,##0")&" @ "&TEXT(Assumptions!$H100,"0%") | F40: =MAX(0,MIN(F$37,Assumptions!$G100)-Assumptions!$F100)*Assumptions!$H100 | G40: =MAX(0,MIN(G$37,Assumptions!$G100)-Assumptions!$F100)*Assumptions!$H100 | H40: =MAX(0,MIN(H$37,Assumptions!$G100)-Assumptions!$F100)*Assumptions!$H100
D41: =TEXT(Assumptions!$F101,"#,##0")&" - "&TEXT(Assumptions!$G101,"#,##0")&" @ "&TEXT(Assumptions!$H101,"0%") | F41: =MAX(0,MIN(F$37,Assumptions!$G101)-Assumptions!$F101)*Assumptions!$H101 | G41: =MAX(0,MIN(G$37,Assumptions!$G101)-Assumptions!$F101)*Assumptions!$H101 | H41: =MAX(0,MIN(H$37,Assumptions!$G101)-Assumptions!$F101)*Assumptions!$H101
D42: =TEXT(Assumptions!$F102,"#,##0")&" - "&TEXT(Assumptions!$G102,"#,##0")&" @ "&TEXT(Assumptions!$H102,"0%") | F42: =MAX(0,MIN(F$37,Assumptions!$G102)-Assumptions!$F102)*Assumptions!$H102 | G42: =MAX(0,MIN(G$37,Assumptions!$G102)-Assumptions!$F102)*Assumptions!$H102 | H42: =MAX(0,MIN(H$37,Assumptions!$G102)-Assumptions!$F102)*Assumptions!$H102
D43: =TEXT(Assumptions!$F103,"#,##0")&" - "&TEXT(Assumptions!$G103,"#,##0")&" @ "&TEXT(Assumptions!$H103,"0%") | F43: =MAX(0,MIN(F$37,Assumptions!$G103)-Assumptions!$F103)*Assumptions!$H103 | G43: =MAX(0,MIN(G$37,Assumptions!$G103)-Assumptions!$F103)*Assumptions!$H103 | H43: =MAX(0,MIN(H$37,Assumptions!$G103)-Assumptions!$F103)*Assumptions!$H103
D44: =TEXT(Assumptions!$F104,"#,##0")&" - "&TEXT(Assumptions!$G104,"#,##0")&" @ "&TEXT(Assumptions!$H104,"0%") | F44: =MAX(0,MIN(F$37,Assumptions!$G104)-Assumptions!$F104)*Assumptions!$H104 | G44: =MAX(0,MIN(G$37,Assumptions!$G104)-Assumptions!$F104)*Assumptions!$H104 | H44: =MAX(0,MIN(H$37,Assumptions!$G104)-Assumptions!$F104)*Assumptions!$H104
D45: =TEXT(Assumptions!$F105,"#,##0")&" - "&TEXT(Assumptions!$G105,"#,##0")&" @ "&TEXT(Assumptions!$H105,"0%") | F45: =MAX(0,MIN(F$37,Assumptions!$G105)-Assumptions!$F105)*Assumptions!$H105 | G45: =MAX(0,MIN(G$37,Assumptions!$G105)-Assumptions!$F105)*Assumptions!$H105 | H45: =MAX(0,MIN(H$37,Assumptions!$G105)-Assumptions!$F105)*Assumptions!$H105
D46: =TEXT(Assumptions!$F106,"#,##0")&" - "&TEXT(Assumptions!$G106,"#,##0")&" @ "&TEXT(Assumptions!$H106,"0%") | F46: =MAX(0,MIN(F$37,Assumptions!$G106)-Assumptions!$F106)*Assumptions!$H106 | G46: =MAX(0,MIN(G$37,Assumptions!$G106)-Assumptions!$F106)*Assumptions!$H106 | H46: =MAX(0,MIN(H$37,Assumptions!$G106)-Assumptions!$F106)*Assumptions!$H106
D47: Total income tax | E47: EUR | F47: =-SUM(F40:F46) | G47: =-SUM(G40:G46) | H47: =-SUM(H40:H46)
D49: 4. Founder net income vs target
D50: Net income available to founder | E50: EUR | F50: =F31+F47 | G50: =G31+G47 | H50: =H31+H47
D51: Months in period | E51: # | F51: 6 | G51: 12 | H51: 12
D52: Average net per month | E52: EUR | F52: =F50/F51 | G52: =G50/G51 | H52: =H50/H51
D53: Target net draw per month | E53: EUR | F53: 3500 | G53: 3500 | H53: 3500
D54: Months at target | E54: # | F54: 0 | G54: 6 | H54: 12
D55: Target net income | E55: EUR | F55: =F53*F54 | G55: =G53*G54 | H55: =H53*H54
D56: Surplus / (gap) vs target | E56: EUR | F56: =F50-F55 | G56: =G50-G55 | H56: =H50-H55

Sheet Salaries
E1: https://bruttonetto.finanzrechner.at/en/
D2: Y1 | E2: Y2 | F2: Y3
C3: Founder | D3: =D8 | E3: =E8 | F3: =F8 | J3: Monthly Employer contributions as % of gross | K3: 0.3
C4: Net monthly salary | D4: 1800 | E4: 1800 | F4: 1800
C5: Yearly salary (net) | D5: =D4*12 | E5: =E4*12 | F5: =F4*12
C6: Gross salary multiplier | D6: 1.3 | E6: 1.3 | F6: 1.3
C7: Gross salary | D7: =D6*D5 | E7: =E6*E5 | F7: =F6*F5
C8: Total cost | D8: =D7*(1+$K$3) | E8: =E7*(1+$K$3) | F8: =F7*(1+$K$3)
C10: Customer support | D10: =D15 | E10: =E15 | F10: =F15 | J10: Monthly Employer contributions as % of gross | K10: 0.3
C11: Net monthly salary | E11: 2500 | F11: =E11
C12: Yearly salary (net) | E12: =E11*12 | F12: =F11*12
C13: Gross salary multiplier | E13: 1.55 | F13: 1.55
C14: Gross salary | E14: =E13*E12 | F14: =F13*F12
C15: Total cost | E15: =E14*(1+$K$3) | F15: =F14*(1+$K$3)
C17: Designer | D17: =D22 | E17: =E22 | F17: =F22 | J17: Monthly Employer contributions as % of gross | K17: 0
C18: Net monthly salary | E18: 3000 | F18: =E18
C19: Yearly salary (net) | D19: =D18*12 | E19: =E18*12 | F19: =F18*12
C20: Gross salary multiplier | E20: 1 | F20: 1
C21: Gross salary | D21: =D20*D19 | E21: =E20*E19 | F21: =F20*F19
C22: Total cost | D22: =D21*(1+$K$3) | E22: =E21*(1+$K$17) | F22: =F21*(1+$K$17)
D24: =SUM(D25:D27) | E24: =SUM(E25:E27) | F24: =SUM(F25:F27)
C25: Employer contributions | D25: =(D8-D5)+(D15-D12) | E25: =(E8-E5)+(E15-E12) | F25: =(F8-F5)+(F15-F12)
C26: Salaries (founder) | D26: =D5 | E26: =E5 | F26: =F5
C27: Salaries (employees) | D27: =D12+D19 | E27: =E12+E19 | F27: =F12+F19

Sheet Assumptions
D2: hard input
D3: link to other cell
D4: calc
D5: not used for calcs
B7: # | D7: Metric | E7: Unit | O7: Comments
B9: 1 | D9: Macro
D11: Inflation | E11: % | F11: 0.02
D12: VAT rate | E12: % | F12: 0.2
B14: 2 | D14: Variable costs
B16: 2.1 | D16: COGS
B18: 2.1.1 | D18: Production and fulfilment
D20: # books/day | E20: pcs | F20: 1 | G20: 2 | H20: 3 | I20: 4 | J20: 5 | K20: 10 | L20: 20 | M20: 50 | N20: 75
D21: # books/month | E21: pcs | F21: =F20*30 | G21: =G20*30 | H21: =H20*30 | I21: =I20*30 | J21: =J20*30 | K21: =K20*30 | L21: =L20*30 | M21: =M20*30 | N21: =N20*30
D23: Printsmarter
D24: Printing/40 pages unit | E24: EUR | F24: =7.35+0.16*7 | G24: =F24 | H24: =G24 | I24: =H24 | J24: =I24 | K24: =J24 | L24: =K24 | M24: =L24 | N24: =M24
D25: Printing/80 pages unit | E25: EUR | F25: =7.35+0.16*27 | G25: =F25 | H25: =G25 | I25: =H25 | J25: =I25 | K25: =J25 | L25: =K25 | M25: =L25 | N25: =M25
D26: Total packaging per unit | F26: =F27+F28+F29 | G26: =G27+G28+G29 | H26: =H27+H28+H29 | I26: =I27+I28+I29 | J26: =J27+J28+J29 | K26: =K27+K28+K29 | L26: =L27+L28+L29 | M26: =M27+M28+M29 | N26: =N27+N28+N29
D27: Packaging/unit | E27: EUR | F27: 2.34 | G27: =F27 | H27: =G27 | I27: =H27 | J27: =I27 | K27: =J27 | L27: =K27 | M27: =L27 | N27: =M27
D28: Sticker/unit | E28: EUR | F28: 0.2 | G28: =F28 | H28: =G28 | I28: =H28 | J28: =I28 | K28: =J28 | L28: =K28 | M28: =L28 | N28: =M28
D29: Flyer/unit | E29: EUR | F29: 0.2 | G29: =F29 | H29: =G29 | I29: =H29 | J29: =I29 | K29: =J29 | L29: =K29 | M29: =L29 | N29: =M29
D30: Delivery/unit AT | E30: EUR | F30: 6.6 | G30: =F30 | H30: =G30 | I30: =H30 | J30: =I30 | K30: =J30 | L30: =K30 | M30: =L30 | N30: =M30
D31: Delivery/unit DE | E31: EUR | F31: 4.9 | G31: =F31 | H31: =G31 | I31: =H31 | J31: =I31 | K31: =J31 | L31: =K31 | M31: =L31 | N31: =M31
D32: Cloud/unit | E32: EUR | F32: 0.04 | G32: =F32 | H32: =G32 | I32: =H32 | J32: =I32 | K32: =J32 | L32: =K32 | M32: =L32 | N32: =M32 | O32: assuming 100-200mb pdf size
D34: Storage costs per pallet per month | E34: EUR | F34: 18.5 | G34: =F34 | H34: =G34 | I34: =H34 | J34: =I34 | K34: =J34 | L34: =K34 | M34: =L34 | N34: =M34 | O34: assuming the same as per Elanders
D36: Elanders
D37: Printing/40 pages unit | E37: EUR | F37: 15.88 | G37: =F37 | H37: =G37 | I37: =H37 | J37: =I37 | K37: 10.71 | L37: 8.03 | M37: 6.43 | N37: 6.09 | O37: 1-5 orders assumed the same for now (at least for 6 months)
D38: Printing/80 pages unit | E38: EUR | F38: =F37+0.15*20 | G38: =G37+0.15*20 | H38: =H37+0.15*20 | I38: =I37+0.15*20 | J38: =J37+0.15*20 | K38: =K37+0.15*20 | L38: =L37+0.15*20 | M38: =M37+0.15*20 | N38: =N37+0.15*20
D39: Total packaging per unit | E39: EUR | F39: =F40+F41+F42 | G39: =G40+G41+G42 | H39: =H40+H41+H42 | I39: =I40+I41+I42 | J39: =J40+J41+J42 | K39: =K40+K41+K42 | L39: =L40+L41+L42 | M39: =M40+M41+M42 | N39: =N40+N41+N42
D40: Packaging/unit | E40: EUR | F40: 2.25 | G40: =F40 | H40: =G40 | I40: =H40 | J40: =I40 | K40: =J40 | L40: =K40 | M40: =L40 | N40: =M40
D41: Sticker/unit | E41: EUR | F41: 0.2 | G41: =F41 | H41: =G41 | I41: =H41 | J41: =I41 | K41: =J41 | L41: =K41 | M41: =L41 | N41: =M41
D42: Flyer/unit | E42: EUR | F42: 0.2 | G42: =F42 | H42: =G42 | I42: =H42 | J42: =I42 | K42: =J42 | L42: =K42 | M42: =L42 | N42: =M42
D43: Delivery/unit AT | E43: EUR | F43: 5.1 | G43: =F43 | H43: =G43 | I43: =H43 | J43: =I43 | K43: =J43 | L43: =K43 | M43: =L43 | N43: =M43
D44: Delivery/unit DE | E44: EUR | F44: 2.95 | G44: =F44 | H44: =G44 | I44: =H44 | J44: =I44 | K44: =J44 | L44: =K44 | M44: =L44 | N44: =M44
D45: Cloud/unit | E45: EUR | F45: 0.04 | G45: =F45 | H45: =G45 | I45: =H45 | J45: =I45 | K45: =J45 | L45: =K45 | M45: =L45 | N45: =M45 | O45: assuming 100-200mb pdf size
D47: Storage costs per pallet per month | E47: EUR | F47: 18.5 | G47: =F47 | H47: =G47 | I47: =H47 | J47: =I47 | K47: =J47 | L47: =K47 | M47: =L47 | N47: =M47
D50: Packaging/unit | E50: EUR | F50: 2.25 | G50: 2.25 | H50: 2.25 | I50: 2.25 | J50: 2.25 | K50: 2.25 | L50: 2.25 | M50: 2.25
D51: Cloud/unit | E51: EUR | F51: 0.04 | G51: 0.04 | H51: 0.04 | I51: 0.04 | J51: 0.04 | K51: 0.04 | L51: 0.04 | M51: 0.04
D52: Delivery/unit | E52: EUR | F52: 0 | G52: 0 | H52: 0 | I52: 0 | J52: 0 | K52: 0 | L52: 0 | M52: 0
D53: Total | E53: EUR | F53: 28.880019 | G53: 18.402871 | H53: 14.998743 | I53: 13.20212 | J53: 12.37 | K53: 12.067411 | L53: 11.424409 | M53: 10.956044
D54: Variable cost factor (10=1), assumed | F54: 1 | G54: 0.7461105 | H54: 0.62367934 | I54: 0.57249458 | J54: 0.54958003 | K54: 0.52555906 | L54: 0.51177448 | M54: 0.36643333
B56: 2.1.2 | D56: Payment processing fees
D58: Visa/Mastercard debit | E58: % from transaction | F58: 0.0089 | L58: nexi.at
D59: Visa/Mastercard credit | E59: % from transaction | F59: 0.0169 | L59: nexi.at
D60: Stripe | E60: % from transaction | F60: 0.015 | L60: nexi.at | P60: =70 | Q60: 0.015 | R60: =P60*Q60 | S60: =P60-R60
P61: =P60 | Q61: =R61/P61 | R61: =P61-S61 | S61: 67.47
D62: Visa/Mastercard debit | E62: fixed fee, EUR | F62: 0.08 | L62: nexi.at
D63: Visa/Mastercard credit | E63: fixed fee, EUR | F63: 0.25 | L63: nexi.at
D64: Stripe | E64: fixed fee, EUR | F64: 0.35 | L64: nexi.at | S64: =S61+S60
D66: Assumed payment mix
D68: Visa/Mastercard debit | E68: % of total transactions | F68: 0.7
D69: Visa/Mastercard credit | E69: % of total transactions | F69: 0.15
D70: Stripe | E70: % of total transactions | F70: 0.15
B74: 2.1.3 | D74: Design fees
D76: Cost per template (40 and 80 pages) with multiple variations | E76: EUR | F76: 500
D77: Royalty fee | E77: % from revenue | F77: 0.03
B81: 2.1.4 | D81: B2B
F82: 2026 | G82: =F82+1 | H82: =G82+1 | I82: 2029
D83: Premium to B2C Price | F83: 0.1 | G83: 0.1 | H83: 0.1 | I83: 0.1
D84: Share of B2B orders from total | F84: 0.02 | G84: 0.04 | H84: 0.06 | I84: 0.08
B87: 2.2 | D87: Austrian tax & social security (Einzelunternehmer)
D89: SVS contributions (sole trader)
D90: Pension insurance (PV) | E90: % of base | F90: 0.185
D91: Health insurance (KV) | E91: % of base | F91: 0.068
D92: Self-employment provision (Selbstaendigenvorsorge) | E92: % of base | F92: 0.0153
D93: Total contribution rate | E93: % of base | F93: =SUM(F90:F92)
D94: Accident insurance (UV), flat | E94: EUR/month | F94: 12.95
D95: Minimum contribution base | E95: EUR/month | F95: 551.1
D96: Maximum contribution base | E96: EUR/month | F96: 8085
D98: Income tax brackets 2026 (progressive)
F99: From (EUR) | G99: To (EUR) | H99: Marginal rate
D100: Tier 1 | F100: 0 | G100: 13539 | H100: 0
D101: Tier 2 | F101: =G100 | G101: 21992 | H101: 0.2
D102: Tier 3 | F102: =G101 | G102: 36458 | H102: 0.3
D103: Tier 4 | F103: =G102 | G103: 70365 | H103: 0.4
D104: Tier 5 | F104: =G103 | G104: 104859 | H104: 0.48
D105: Tier 6 | F105: =G104 | G105: 1000000 | H105: 0.5
D106: Tier 7 | F106: =G105 | G106: 999999999 | H106: 0.55
D108: Gewinnfreibetrag & loss relief
D109: Grundfreibetrag rate | E109: % of profit | F109: 0.15
D110: Profit cap for Grundfreibetrag | E110: EUR | F110: 33000
D111: Max Grundfreibetrag | E111: EUR | F111: =F109*F110
D112: Loss carry-forward offsettable | E112: % of income | F112: 1
D114: Customer delivery charge AT (face value) | E114: EUR | F114: 4.99 | O114: Capped on par with CEWE. Aevia subsidises the rest of the ~6.60 carrier cost.

Sheet Sheet1
E3: extras | H3: delivery options
B4: Size | C4: Price (excl. delivery) | D4: # photos | E4: gift wrap | F4: free shipping | G4: perks | H4: free | I4: standard | J4: express
A5: Journi | B5: 40 pages | C5: 43 | D5: 56 | E5: 2.99 | F5: from 60 | G5: 20% off with registration | H5: ~10 working days | I5: 4.99 (7 working days) | J5: 9.99 (6 working days)
A6: CEWE | B6: 42 pages | C6: 55.15 | D6: 56 | E6: 4.99 | H6: - | I6: 5.49 (6-7 working days) | J6: 12.99 (6 working days)

Sheet Journi sanity check
C3: Aug | D3: Sep | E3: Oct | F3: MAU,k
B4: Journi | C4: 331.4 | D4: 328.8 | E4: 252.4 | F4: =AVERAGE(C4:E4)
B6: bounce rate | C6: 0.4456
B8: Top-5 countries
D9: MAU by country,k | E9: monthly purchase, k | F9: yearly purchase
B10: US | C10: 0.1929 | D10: =C10*$F$4 | E10: =D10*$C$24 | F10: =E10*12
B11: Germany | C11: 0.1642 | D11: =C11*$F$4 | E11: =D11*$C$24 | F11: =E11*12
B12: France | C12: 0.1235 | D12: =C12*$F$4 | E12: =D12*$C$24 | F12: =E12*12
B13: Italy | C13: 0.1126 | D13: =C13*$F$4 | E13: =D13*$C$24 | F13: =E13*12
B14: Austria | C14: 0.0602 | D14: =C14*$F$4 | E14: =D14*$C$24 | F14: =E14*12
B15: Other | C15: =1-SUM(C10:C14) | D15: =C15*$F$4 | E15: =D15*$C$24 | F15: =E15*12
F16: =SUM(F10:F15)
B19: Conversion rates (visits to purchase) | E19: https://gripsintelligence.com/insights/retailers/mixbook.com?utm_source=chatgpt.com
B21: Mixbook | C21: 0.0225
B22: Milk books | C22: 0.0325
B23: Artifact Uprising | C23: 0.0425
C24: =AVERAGE(C21:C23)
B26: Annual revenue 2024, EUR | C26: =20*10^6 | D26: https://www.trendingtopics.eu/das-grosse-trending-topics-jahres-voting-2024-software/
B28: Journi book price
C29: EUR
B30: Europe | C30: 45
B31: US | C31: 60
B32: Average price | C32: =C31*C10+C30*(1-C10)
B34: # orders / year | C34: =C26/C32
B36: orders from AT/year | C36: =C34*C14
B37: monthly | C37: =C36/12

Sheet Fotobook.at
C3: Aug | D3: Sep | E3: Oct | F3: MAU,k
B4: fotobook.at | C4: 2.8 | D4: 6.4 | E4: 3 | F4: =AVERAGE(C4:E4)
B6: bounce rate | C6: 0.5259
B8: Top-5 countries
D9: MAU by country,k | E9: monthly purchase, k | F9: yearly purchase
B10: Austria | C10: 0.6745 | D10: =C10*$F$4 | E10: =D10*$C$20 | F10: =E10*12
B11: Germany | C11: 0.3255 | D11: =C11*$F$4 | E11: =D11*$C$20 | F11: =E11*12
F12: =SUM(F10:F11)
B15: Conversion rates (visits to purchase) | E15: https://gripsintelligence.com/insights/retailers/mixbook.com?utm_source=chatgpt.com
B17: Mixbook | C17: 0.0225
B18: Milk books | C18: 0.0325
B19: Artifact Uprising | C19: 0.0425
C20: =AVERAGE(C17:C19)
B22: Annual revenue 2024, EUR | C22: =15*10^6 | D22: https://www.dnb.com/business-directory/company-information.professional_and_commercial_equipment_and_supplies_merchant_wholesalers.at.html?page=5
B23: % of fotobooks revenue | C23: 0.7
C24: =C23*C22 | D24: =C24*C23*C10
B26: Photobook price
C27: EUR
B28: Europe | C28: 50
B30: # orders / year | C30: =C24/C28
B32: orders from AT/year | C32: =C30*C10 | D32: =D24/C28
B33: monthly | C33: =C32/12
C35: 500
C36: =C35/C33

Sheet Printing facilities
B2: # | C2: Name | D2: Country | E2: Link | F2: Sent request? | G2: Received reply? | H2: ball on side | I2: Comments
B3: 1 | C3: Elanders | D3: Poland | E3: https://www.elanders.com/pol/print-products/ | F3: yes | G3: good answers | H3: their | I3: have API
B4: 2 | C4: Flyeralarm | D4: Germany | E4: https://www.flyeralarm.com/de/i/kontakt | F4: no | G4: yes, use calculator from the site | H4: my | I4: 9-11 days printing lead time, no personalized packaging, no API
B5: 3 | C5: Saal | D5: Germany | E5: https://www.saal-digital.eu/support/contact-customer-care/ | F5: yes | G5: good answer to continue (aquamarinkoo mail) | H5: my
B6: 4 | C6: Sowadruck | D6: Poland | E6: https://sowadruk.pl/en/contact | F6: yes | G6: Not working for us | H6: discard
B7: 5 | C7: Druck.pl | D7: Poland | E7: https://druck.pl/kontaktde/ | F7: yes | G7: no answer | H7: discard
B8: 6 | C8: printhub.eu | D8: Poland | E8: https://www.printhub.eu/books-printing-on-demand | F8: yes | G8: good answer to estimate | H8: my | I8: 1 week production time, no API
B9: 7 | C9: graspo | D9: Czech | E9: https://www.graspo.com/en/contact-us | F9: yes | G9: Not working for us | H9: discard
L11: =1620/100
D14: Hub | E14: Digital press (HP Indigo, Ricoh Pro, etc.) | F14: <1w production lead time (from order to delivery) | G14: Uncoated 150–170 gsm stock (or willing to special-order) | H14: Hardcover case-binding: photo-laminate | I14: Branded single-book packaging service | J14: Order automation (API or SFTP)
D15: Elanders | E15: yes | F15: yes | G15: yes | H15: yes | I15: yes | J15: yes
D16: Flyeralarm | E16: yes | F16: yes | G16: yes | H16: yes | I16: n/a | J16: ?
D17: Saal | E17: yes | F17: yes | G17: yes | H17: yes | I17: yes | J17: no
D18: Sowadruck | E18: yes | F18: no | G18: n/a | H18: n/a | I18: n/a | J18: n/a
D19: Druck.pl | E19: n/a | F19: n/a | G19: n/a | H19: n/a | I19: n/a | J19: n/a
D20: printhub.eu | E20: yes | F20: yes | G20: yes | H20: yes | I20: n/a | J20: no
D21: graspo | E21: yes | F21: no | G21: n/a | H21: n/a | I21: n/a | J21: no
D22: Dora

Sheet Grants and accelerators
C2: Perks | D2: Who | E2: Deadline | F2: Link
B3: Startup Scholarship | C3: 8000 | D3: wirtschaftsagentur.at | E3: 15 Septermber | F3: https://wirtschaftsagentur.at/aktuelle-foerderungen-der-wirtschaftsagentur-wien/foe-gruendungsstipendium/
B4: Founders Lab - Creative Industries | C4: mentoring | D4: Vienna Business Services | E4: 17 September - 12.12 | F4: https://vienna.business/events-workshops/founders-lab-creative-industries-2025/
B5: Creative industries funding | C5: up to 200k | D5: Vienna business agency | E5: 31 November | F5: https://wirtschaftsagentur.at/aktuelle-foerderungen-der-wirtschaftsagentur-wien/foerderung-projekt-kreativwirtschaft/

Sheet papers
D1: Density
B2: Paper reference | C2: Mohawk Option Smoth | D2: 148g/m2
B3: Soft cover reference | C3: Mohawk Eggshell | D3: 324g/m2
B7: Printing machine reference | C7: RIKO 9210 (9200) | K7: Gmund
B8: Printing method | C8: offset printing | J8: pcs | K8: 2000
J9: eur | K9: 544.43
J10: eur/pcs | K10: =K9/K8
B13: Printing paper
C14: Country | D14: Offers printing? | E14: Paper reference
B15: gmund.com | C15: Germany | D15: yes | E15: https://www.gmund.com/shop/de_at/780-digi50.html
